com/__init__.py
com/github/__init__.py
com/github/jelmerk/__init__.py
com/github/jelmerk/spark/__init__.py
com/github/jelmerk/spark/conversion/__init__.py
com/github/jelmerk/spark/knn/__init__.py
com/github/jelmerk/spark/knn/bruteforce/__init__.py
com/github/jelmerk/spark/knn/evaluation/__init__.py
com/github/jelmerk/spark/knn/hnsw/__init__.py
com/github/jelmerk/spark/linalg/__init__.py
pyspark_hnsw/__init__.py
pyspark_hnsw/conversion.py
pyspark_hnsw/evaluation.py
pyspark_hnsw/knn.py
pyspark_hnsw/linalg.py
hnswlib_spark-2.0.0a10.dist-info/METADATA
hnswlib_spark-2.0.0a10.dist-info/WHEEL
hnswlib_spark-2.0.0a10.dist-info/top_level.txt
hnswlib_spark-2.0.0a10.dist-info/RECORD
