Metadata-Version: 2.2
Name: hnswlib-spark
Version: 2.0.0a10
Summary: Pyspark module for hnswlib
Home-page: https://github.com/jelmerk/hnswlib/tree/master/hnswlib-pyspark
License: Apache License 2.0
Classifier: License :: OSI Approved :: Apache Software License
Classifier: Programming Language :: Python :: 3
Classifier: Programming Language :: Python :: 3.7
Classifier: Programming Language :: Python :: 3.8
Classifier: Programming Language :: Python :: 3.9
Classifier: Programming Language :: Python :: 3.10
Classifier: Operating System :: OS Independent
Requires-Python: >=3.7
Dynamic: classifier
Dynamic: home-page
Dynamic: license
Dynamic: requires-python
Dynamic: summary
